wstube/__init__.py
pwntools_tube_websocket-0.0.5.dist-info/METADATA
pwntools_tube_websocket-0.0.5.dist-info/WHEEL
pwntools_tube_websocket-0.0.5.dist-info/top_level.txt
pwntools_tube_websocket-0.0.5.dist-info/RECORD
